{
  "bosh-url": "https://x.x.x.x",
  "bosh-port": "25555",
  "bosh-user": "director",
  "diego-brain-disk-type": "51200",
  "diego-cell-disk-type": "51200",
  "mysql-disk-type": "51200",
  "nfs-disk-type": "51200",
  "diego-cell-vm-type": "large",
  "nfs-vm-type": "large",
  "router-vm-type": "large",
  "haproxy-vm-type": "large",
  "nats-vm-type": "large",
  "consul-vm-type": "large",
  "etcd-vm-type": "large",
  "loggregator-traffic-controller-vmtype": "large",
  "mysql-vm-type": "large",
  "mysql-proxy-vm-type": "large",
  "cc-worker-vm-type": "large",
  "cc-vm-type": "large",
  "diego-db-vm-type": "large",
  "diego-brain-vm-type": "large",
  "clock-global-vm-type": "large",
  "doppler-vm-type": "large",
  "uaa-vm-type": "large",
  "errand-vm-type": "large",
  "app-domain": "",
  "system-domain": "",
  "nfs-allow-from-network-cidr": "",
  "nfs-ip": "",
  "mysql-ip": "",
  "diego-cell-ip": "",
  "consul-ip": "",
  "doppler-ip": "",
  "mysql-proxy-ip": "",
  "loggregator-traffic-controller-ip": "",
  "nats-machine-ip": "",
  "etcd-machine-ip": "",
  "diego-brain-ip": "",
  "diego-db-ip": "",
  "router-ip": ""
}
